README.md
setup.py
gotypist_stats/__init__.py
gotypist_stats/__main__.py
gotypist_stats/helper.py
gotypist_stats/report.py
gotypist_stats.egg-info/PKG-INFO
gotypist_stats.egg-info/SOURCES.txt
gotypist_stats.egg-info/dependency_links.txt
gotypist_stats.egg-info/entry_points.txt
gotypist_stats.egg-info/requires.txt
gotypist_stats.egg-info/top_level.txt