Metadata-Version: 2.1
Name: gotypist-stats
Version: 1.1.2
Summary: Get high-level metrics from your gotypist training sessions
Home-page: https://github.com/ssimono/gotypist-stats
Author: Simon Alfassa
Author-email: simon@sa-web.fr
License: MIT
Keywords: gotypist typing statistics
Platform: UNKNOWN
Classifier: Programming Language :: Python :: 3
Classifier: License :: OSI Approved :: MIT License
Classifier: Operating System :: OS Independent
Classifier: Development Status :: 5 - Production/Stable
Classifier: Environment :: Console
Classifier: Intended Audience :: End Users/Desktop
Classifier: Natural Language :: English
Classifier: Topic :: Education
Requires-Python: >=3.6
Provides-Extra: dev
